pytoolbox_talw3g/__init__.py
pytoolbox_talw3g/colortxt.py
pytoolbox_talw3g/confirm.py
pytoolbox_talw3g-0.2.dist-info/METADATA
pytoolbox_talw3g-0.2.dist-info/WHEEL
pytoolbox_talw3g-0.2.dist-info/licenses/LICENSE
pytoolbox_talw3g-0.2.dist-info/RECORD
