Metadata-Version: 2.1
Name: pytoolbox_talw3g
Version: 0.2
Summary: A small package with useful simple tools
Project-URL: Homepage, https://github.com/Talw3g/pytoolbox
Project-URL: Bug Tracker, https://github.com/Talw3g/pytoolbox/issues
Author-email: Thibault MARION <pytoolbox@otter.mozmail.com>
License-File: LICENSE
Classifier: License :: OSI Approved :: MIT License
Classifier: Operating System :: OS Independent
Classifier: Programming Language :: Python :: 3
Requires-Python: >=3.7
